mimseq/__init__.py
mimseq/ccaPlots.R
mimseq/coveragePlot.R
mimseq/crosstalks.py
mimseq/deseq.R
mimseq/getCoverage.py
mimseq/mimseq.py
mimseq/mmQuant.py
mimseq/modPlot.R
mimseq/modifications
mimseq/splitClusters.py
mimseq/ssAlign.py
mimseq/tRNAmap.py
mimseq/tRNAtools.py
mimseq/version.py
mimseq/data/additionalMods.txt
mimseq/data/additionalMods_all.txt
mimseq/data/additionalMods_original.txt
mimseq/data/modomics
mimseq/data/tRNAmatureseq.cm
mimseq/data/araTha1-eColitK/FastaHeadersforMimseq.py
mimseq/data/araTha1-eColitK/README.txt
mimseq/data/araTha1-eColitK/araTha1-PtRNAdb-mito-searchResults.txt
mimseq/data/araTha1-eColitK/araTha1-PtRNAdb-plastid-searchResults.txt
mimseq/data/araTha1-eColitK/araTha1-filtered-tRNAs.fa
mimseq/data/araTha1-eColitK/araTha1-mature-tRNAs.fa
mimseq/data/araTha1-eColitK/araTha1-mitotRNAs.fa
mimseq/data/araTha1-eColitK/araTha1-plastidtRNAs.fa
mimseq/data/araTha1-eColitK/araTha1-tRNAs-all.fa
mimseq/data/araTha1-eColitK/araTha1-tRNAs-confidence-set.out
mimseq/data/araTha1-eColitK/araTha1-tRNAs-confidence-set.ss
mimseq/data/araTha1-eColitK/araTha1-tRNAs-detailed.out
mimseq/data/araTha1-eColitK/araTha1-tRNAs-detailed.ss
mimseq/data/araTha1-eColitK/araTha1-tRNAs.bed
mimseq/data/araTha1-eColitK/araTha1-tRNAs.fa
mimseq/data/araTha1-eColitK/araTha1-tRNAs_name_map.txt
mimseq/data/araTha1-eColitK/convertPtRNAdbSearch.py
mimseq/data/araTha1-eColitK/hg38README.txt
mimseq/data/ce11-eColitK/FastaHeadersforMimseq.py
mimseq/data/ce11-eColitK/README.txt
mimseq/data/ce11-eColitK/ce11-mitotRNAs.fa
mimseq/data/ce11-eColitK/ce11-tRNAs-all.fa
mimseq/data/ce11-eColitK/ce11-tRNAs-all.tmp.fa
mimseq/data/ce11-eColitK/ce11-tRNAs-detailed.out
mimseq/data/ce11-eColitK/ce11-tRNAs-filtered.fa
mimseq/data/ce11-eColitK/ce11-tRNAs.bed
mimseq/data/ce11-eColitK/ce11-tRNAs_name_map.txt
mimseq/data/danRer11-eColitK/README.txt
mimseq/data/danRer11-eColitK/danRer11-mitotRNAs.fa
mimseq/data/danRer11-eColitK/danRer11-tRNAs.bed
mimseq/data/danRer11-eColitK/danRer11_eColitK.fa
mimseq-1.3.9.dist-info/LICENSE.txt
mimseq-1.3.9.dist-info/METADATA
mimseq-1.3.9.dist-info/WHEEL
mimseq-1.3.9.dist-info/entry_points.txt
mimseq-1.3.9.dist-info/top_level.txt
mimseq-1.3.9.dist-info/RECORD
