Metadata-Version: 2.1
Name: mimseq
Version: 1.3.9
Summary: Custom high-throughput tRNA sequencing alignment and quantification pipeline based on modification induced misincorporation cDNA synthesis.
Home-page: https://github.com/nedialkova-lab/mim-tRNAseq
Author: Drew Behrens
Author-email: abehrens@biochem.mpg.de
License: GPLv3
Classifier: Development Status :: 4 - Beta
Classifier: Environment :: Console
Classifier: Intended Audience :: Science/Research
Classifier: License :: OSI Approved :: GNU General Public License v3 (GPLv3)
Classifier: Natural Language :: English
Classifier: Programming Language :: Python :: 3
Classifier: Topic :: Scientific/Engineering :: Bio-Informatics
License-File: LICENSE.txt
Requires-Dist: biopython
Requires-Dist: pandas
Requires-Dist: numpy
Requires-Dist: pyfiglet
Requires-Dist: pysam
Requires-Dist: pytest
Requires-Dist: seaborn
Requires-Dist: matplotlib
Requires-Dist: pybedtools
Requires-Dist: requests
Requires-Dist: statsmodels
